pyvol/__init__.py
pyvol/__main__.py
pyvol/cluster.py
pyvol/configuration.py
pyvol/construct.py
pyvol/exceptions.py
pyvol/identify.py
pyvol/poses.py
pyvol/pymol_interface.py
pyvol/pymol_utilities.py
pyvol/spheres.py
pyvol/utilities.py
bio_pyvol-1.7.8.dist-info/LICENSE.txt
bio_pyvol-1.7.8.dist-info/METADATA
bio_pyvol-1.7.8.dist-info/WHEEL
bio_pyvol-1.7.8.dist-info/entry_points.txt
bio_pyvol-1.7.8.dist-info/top_level.txt
bio_pyvol-1.7.8.dist-info/RECORD
