Metadata-Version: 2.1
Name: bio-pyvol
Version: 1.7.8
Summary: a PyMOL plugin and python package for visualization, comparison, and volume calculation of protein drug-binding sites
Home-page: https://github.com/schlessinger-lab/pyvol
Author: Ryan H.B. Smith
Author-email: ryan.smith@icahn.mssm.edu
License: MIT
Platform: UNKNOWN
Classifier: License :: OSI Approved :: MIT License
Classifier: Programming Language :: Python :: 3.7
Requires-Dist: biopython (>=1.73)
Requires-Dist: numpy (>=1.16.1)
Requires-Dist: pandas (>=0.24.1)
Requires-Dist: scipy (>=1.2.1)
Requires-Dist: scikit-learn (>=0.20.2)
Requires-Dist: trimesh (>=2.36.29)
Requires-Dist: configparser
